data_agent_zip/__init__.py
data_agent_zip/connector.py
data_agent_zip-0.1.2.dist-info/LICENSE.txt
data_agent_zip-0.1.2.dist-info/METADATA
data_agent_zip-0.1.2.dist-info/WHEEL
data_agent_zip-0.1.2.dist-info/entry_points.txt
data_agent_zip-0.1.2.dist-info/top_level.txt
data_agent_zip-0.1.2.dist-info/RECORD
