Metadata-Version: 2.1
Name: data-agent-zip
Version: 0.1.2
Summary: ZIP files plugin for `data-agent` package
Home-page: https://github.com/imubit/data-agent-zip/
Author: Meir Tseitlin
Author-email: meir@imubit.com
License: LGPLv3
Project-URL: Documentation, https://github.com/imubit/data-agent-zip/
Project-URL: Source, https://github.com/imubit/data-agent-zip/
Platform: any
Classifier: Development Status :: 4 - Beta
Classifier: Programming Language :: Python
License-File: LICENSE.txt
Requires-Dist: pandas
Requires-Dist: data-agent
Requires-Dist: importlib-metadata ; python_version < "3.8"
Provides-Extra: testing
Requires-Dist: setuptools ; extra == 'testing'
Requires-Dist: pytest ; extra == 'testing'
Requires-Dist: pytest-cov ; extra == 'testing'
